flawless/__init__.py
flawless/client/__init__.py
flawless/client/client.py
flawless/client/decorators.py
flawless/client/middleware.py
flawless/lib/__init__.py
flawless/lib/utils.py
flawless/lib/config/__init__.py
flawless/lib/config/config.py
flawless/lib/data_structures/__init__.py
flawless/lib/data_structures/lru_cache.py
flawless/lib/data_structures/persistent_dictionary.py
flawless/lib/data_structures/prefix_tree.py
flawless/lib/data_structures/proxy_container.py
flawless/lib/storage/__init__.py
flawless/lib/storage/base.py
flawless/lib/storage/disk.py
flawless/lib/storage/redis.py
flawless/lib/storage/stub.py
flawless/lib/version_control/__init__.py
flawless/lib/version_control/repo.py
flawless/server/__init__.py
flawless/server/configure_server.py
flawless/server/manage.py
flawless/server/server.py
flawless/server/service.py
flawless/server/stub.py
flawless/server/webapp.py
flawless/server/api/Flawless.py
flawless/server/api/__init__.py
flawless/server/api/constants.py
flawless/server/api/ttypes.py
flawless-0.4.5.data/data/config/flawless.cfg
flawless-0.4.5.dist-info/LICENSE
flawless-0.4.5.dist-info/METADATA
flawless-0.4.5.dist-info/WHEEL
flawless-0.4.5.dist-info/entry_points.txt
flawless-0.4.5.dist-info/top_level.txt
flawless-0.4.5.dist-info/RECORD
