Metadata-Version: 2.1
Name: flawless
Version: 0.4.5
Summary: Python Error Monitoring and Reporting
Home-page: http://github.com/shopkick/flawless
Author: John Egan
Author-email: jwegan@gmail.com
License: MPL 2.0
Platform: UNKNOWN
Classifier: Development Status :: 5 - Production/Stable
Classifier: Framework :: Pylons
Classifier: Framework :: Django
Classifier: Framework :: Pyramid
Classifier: Framework :: Paste
Classifier: Intended Audience :: Developers
Classifier: License :: OSI Approved :: Mozilla Public License 2.0 (MPL 2.0)
Classifier: Programming Language :: Python :: 2
Classifier: Programming Language :: Python :: 2.7
Classifier: Programming Language :: Python :: 3
Classifier: Programming Language :: Python :: 3.6
Classifier: Topic :: Software Development :: Bug Tracking
Classifier: Topic :: Software Development :: Quality Assurance
Requires-Dist: future
Requires-Dist: thrift (>=0.10.0)
